discord/ext/track_edits/__init__.py
discord/ext/track_edits/_lock.py
discord/ext/track_edits/_types.py
discord/ext/track_edits/cog.py
discord/ext/track_edits/context.py
discord/ext/track_edits/py.typed
discord_ext_track_edits-0.1.2.dist-info/WHEEL
discord_ext_track_edits-0.1.2.dist-info/METADATA
discord_ext_track_edits-0.1.2.dist-info/RECORD
