Metadata-Version: 2.4
Name: discord-ext-track-edits
Version: 0.1.2
Summary: A discord.py extension for automatic edit tracking
Keywords: discord,edit tracking,extension,discord-ext
Author: beerpsi
Author-email: beerpsi <beerpsi@duck.com>
License-Expression: MIT
Classifier: Development Status :: 3 - Alpha
Classifier: Intended Audience :: Developers
Classifier: License :: OSI Approved :: MIT License
Classifier: Programming Language :: Python :: 3.8
Classifier: Programming Language :: Python :: 3.9
Classifier: Programming Language :: Python :: 3.10
Classifier: Programming Language :: Python :: 3.11
Classifier: Programming Language :: Python :: 3.12
Classifier: Programming Language :: Python :: 3.13
Classifier: Topic :: Communications :: Chat
Classifier: Typing :: Typed
Requires-Dist: discord-py>=2.5.2
Requires-Dist: typing-extensions>=4.13.2
Requires-Python: >=3.8
Project-URL: Homepage, https://github.com/beer-psi/discord-ext-track-edits
Project-URL: Issues, https://github.com/beer-psi/discord-ext-track-edits/issues
Project-URL: Repository, https://github.com/beer-psi/discord-ext-track-edits.git
